aiohttp_valera_validator/__init__.py
aiohttp_valera_validator/_validate.py
aiohttp_valera_validator/py.typed
aiohttp_valera_validator-0.1.1.dist-info/LICENSE
aiohttp_valera_validator-0.1.1.dist-info/METADATA
aiohttp_valera_validator-0.1.1.dist-info/WHEEL
aiohttp_valera_validator-0.1.1.dist-info/top_level.txt
aiohttp_valera_validator-0.1.1.dist-info/RECORD
