Metadata-Version: 2.1
Name: aiohttp-valera-validator
Version: 0.1.1
Summary: Request validation for aiohttp
Home-page: https://github.com/tsv1/aiohttp-valera-validator
Author: Nikita Tsvetkov
Author-email: tsv1@fastmail.com
License: Apache-2.0
Classifier: License :: OSI Approved :: Apache Software License
Classifier: Programming Language :: Python :: 3.8
Classifier: Programming Language :: Python :: 3.9
Classifier: Programming Language :: Python :: 3.10
Classifier: Typing :: Typed
Requires-Python: >=3.8
License-File: LICENSE
Requires-Dist: aiohttp<4.0,>=3.5
Requires-Dist: multidict<7.0,>=4.5
Requires-Dist: valera<2.0,>=1.5
